pillowdrawtable/__init__.py
pillowdrawtable/drawtable.py
pillowdrawtable-0.1.4.1.dist-info/LICENSE
pillowdrawtable-0.1.4.1.dist-info/METADATA
pillowdrawtable-0.1.4.1.dist-info/WHEEL
pillowdrawtable-0.1.4.1.dist-info/top_level.txt
pillowdrawtable-0.1.4.1.dist-info/RECORD
