Metadata-Version: 2.1
Name: pillowdrawtable
Version: 0.1.4.1
Summary: Draw a table in pillow image
Home-page: https://github.com/dhanushnayak/drawpillowtable
Author: Dhanush Nayak
Author-email: dhanushnayak.pythonnotebook@gmail.com
License: MIT
Keywords: Pillow,Table
Platform: UNKNOWN
Requires-Python: >=3.6
License-File: LICENSE
Requires-Dist: Pillow (==9.0.1)
